setup.cfg
setup.py
sentry_javascript_lite/__init__.py
sentry_javascript_lite/plugin.py
sentry_javascript_lite.egg-info/PKG-INFO
sentry_javascript_lite.egg-info/SOURCES.txt
sentry_javascript_lite.egg-info/dependency_links.txt
sentry_javascript_lite.egg-info/entry_points.txt
sentry_javascript_lite.egg-info/not-zip-safe
sentry_javascript_lite.egg-info/requires.txt
sentry_javascript_lite.egg-info/top_level.txt